Metadata-Version: 2.4
Name: gu-django-filebrowser-no-grappelli
Version: 3.3.3
Summary: Media-Management with the Django Admin-Interface. Without django-grappelli requirement.
Home-page: https://github.com/hu-django/filebrowser-no-grappelli
Author: Patrick Kranzlmueller
Author-email: patrick@vonautomatisch.at
Classifier: Development Status :: 4 - Beta
Classifier: Environment :: Web Environment
Classifier: Intended Audience :: Developers
Classifier: License :: OSI Approved :: BSD License
Classifier: Operating System :: OS Independent
Classifier: Programming Language :: Python
Classifier: Programming Language :: Python :: 3
Classifier: Framework :: Django
License-File: LICENSE
Requires-Dist: Django<6.0,>=3.2
Requires-Dist: Pillow<10
Dynamic: author
Dynamic: author-email
Dynamic: classifier
Dynamic: home-page
Dynamic: license-file
Dynamic: requires-dist
Dynamic: summary
